[
    {
      "quote": "The only way to achieve the impossible is to believe it is possible.",
      "author": "Charles Kingsleigh"
    },
    {
      "quote": "The future belongs to those who believe in the beauty of their dreams.",
      "author": "Eleanor Roosevelt"
    },
    {
      "quote": "Success is not in what you have, but who you are.",
      "author": "Bo Bennett"
    },
    {
      "quote": "The only limit to our realization of tomorrow will be our doubts of today.",
      "author": "Franklin D. Roosevelt"
    },
    {
      "quote": "Believe you can and you're halfway there.",
      "author": "Theodore Roosevelt"
    },
    {
      "quote": "It always seems impossible until it's done.",
      "author": "Nelson Mandela"
    },
    {
      "quote": "Your attitude, not your aptitude, will determine your altitude.",
      "author": "Zig Ziglar"
    },
    {
      "quote": "You are never too old to set another goal or to dream a new dream.",
      "author": "C.S. Lewis"
    },
    {
      "quote": "The only way to do great work is to love what you do.",
      "author": "Steve Jobs"
    },
    {
      "quote": "The harder you work for something, the greater you'll feel when you achieve it.",
      "author": "Unknown"
    }
  ]
  